odoo/addons/project_task_dependency/README.rst
odoo/addons/project_task_dependency/__init__.py
odoo/addons/project_task_dependency/__manifest__.py
odoo/addons/project_task_dependency/i18n/it.po
odoo/addons/project_task_dependency/i18n/project_task_dependency.pot
odoo/addons/project_task_dependency/migrations/15.0.1.0.0/pre-migration.py
odoo/addons/project_task_dependency/readme/CONTRIBUTORS.rst
odoo/addons/project_task_dependency/readme/DESCRIPTION.rst
odoo/addons/project_task_dependency/static/description/icon.png
odoo/addons/project_task_dependency/static/description/index.html
odoo_addon_project_task_dependency-15.0.1.0.0.5.dist-info/METADATA
odoo_addon_project_task_dependency-15.0.1.0.0.5.dist-info/WHEEL
odoo_addon_project_task_dependency-15.0.1.0.0.5.dist-info/top_level.txt
odoo_addon_project_task_dependency-15.0.1.0.0.5.dist-info/RECORD
